MDP/__init__.py
MDP/mdp.py
marketdp-0.2.0.dist-info/METADATA
marketdp-0.2.0.dist-info/WHEEL
marketdp-0.2.0.dist-info/top_level.txt
marketdp-0.2.0.dist-info/RECORD
