Metadata-Version: 2.4
Name: marketDP
Version: 0.2.0
Summary: simple python code for predicting markets
Author: navidpgg
Requires-Dist: scikit-learn
Requires-Dist: numpy
Dynamic: author
Dynamic: description
Dynamic: description-content-type
Dynamic: requires-dist
Dynamic: summary
